contextcrunch/__init__.py
contextcrunch/client.py
contextcrunch-1.0.4.dist-info/METADATA
contextcrunch-1.0.4.dist-info/WHEEL
contextcrunch-1.0.4.dist-info/licenses/LICENSE
contextcrunch-1.0.4.dist-info/RECORD
