Metadata-Version: 2.1
Name: contextcrunch
Version: 1.0.4
Summary: Access to the ContextCrunch Prompt Compression API from Python
Project-URL: Homepage, https://github.com/contextcrunch-ai/contextcrunch-python
Project-URL: Issues, https://github.com/contextcrunch-ai/contextcrunch-python/issues
Author-email: Matthew Kwiatkowski <matt@mkcodes.ca>
License-File: LICENSE
Classifier: License :: OSI Approved :: MIT License
Classifier: Operating System :: OS Independent
Classifier: Programming Language :: Python :: 3
Requires-Python: >=3.8
Requires-Dist: requests>=2.25.1
